hadrian/__init__.py
hadrian/conf/__init__.py
hadrian/conf/fab.py
hadrian/contrib/__init__.py
hadrian/contrib/auth/__init__.py
hadrian/contrib/auth/decorators.py
hadrian/contrib/auth/templatetags/__init__.py
hadrian/contrib/auth/templatetags/group_tags.py
hadrian/contrib/google/__init__.py
hadrian/contrib/gravatar/__init__.py
hadrian/contrib/gravatar/templates/gravatar/get_gravatar.html
hadrian/contrib/gravatar/templates/gravatar/gravatar.html
hadrian/contrib/gravatar/templatetags/__init__.py
hadrian/contrib/gravatar/templatetags/gravatar_tags.py
hadrian/contrib/pagination/__init__.py
hadrian/contrib/pagination/templatetags/__init__.py
hadrian/contrib/pagination/templatetags/pagination.py
hadrian-2.0.dist-info/DESCRIPTION.rst
hadrian-2.0.dist-info/METADATA
hadrian-2.0.dist-info/metadata.json
hadrian-2.0.dist-info/RECORD
hadrian-2.0.dist-info/top_level.txt
hadrian-2.0.dist-info/WHEEL
