Metadata-Version: 2.0
Name: hadrian
Version: 2.0
Summary: A Collection of Django packages and scripts
Home-page: http://github.com/dstegelman/hadrian
Author: Derek Stegelman, Garrett Pennington
Author-email: dstegelman@gmail.com
License: MIT
Platform: UNKNOWN
Classifier: Development Status :: 5 - Production/Stable
Classifier: Environment :: Web Environment
Classifier: Intended Audience :: End Users/Desktop
Classifier: Natural Language :: English
Classifier: Operating System :: OS Independent
Classifier: Framework :: Django
Classifier: Programming Language :: Python
Classifier: Topic :: Internet :: WWW/HTTP :: Dynamic Content :: CGI Tools/Libraries
Classifier: Topic :: Utilities
Classifier: License :: OSI Approved :: MIT License
